setup.py
world_mkts_data/__init__.py
worldmkts.egg-info/PKG-INFO
worldmkts.egg-info/SOURCES.txt
worldmkts.egg-info/dependency_links.txt
worldmkts.egg-info/requires.txt
worldmkts.egg-info/top_level.txt