Metadata-Version: 1.0
Name: worldmkts
Version: 0.1
Summary: Display World Markets data from Google Finance
Home-page: UNKNOWN
Author: David Elden
Author-email: UNKNOWN
License: UNKNOWN
Platform: UNKNOWN
